tkinter_embedded/__init__.py
tkinter_embedded/__main__.py
tkinter_embedded/_tkinter.cpython-313-darwin.so
tkinter_embedded/colorchooser.py
tkinter_embedded/commondialog.py
tkinter_embedded/constants.py
tkinter_embedded/dialog.py
tkinter_embedded/dnd.py
tkinter_embedded/filedialog.py
tkinter_embedded/font.py
tkinter_embedded/messagebox.py
tkinter_embedded/scrolledtext.py
tkinter_embedded/simpledialog.py
tkinter_embedded/ttk.py
tkinter_embedded/version.py
tkinter_embedded/Tcl.framework/Tcl
tkinter_embedded/Tcl.framework/libtclstub.a
tkinter_embedded/Tcl.framework/tclConfig.sh
tkinter_embedded/Tcl.framework/Headers/tcl.h
tkinter_embedded/Tcl.framework/Headers/tclDecls.h
tkinter_embedded/Tcl.framework/Headers/tclOO.h
tkinter_embedded/Tcl.framework/Headers/tclOODecls.h
tkinter_embedded/Tcl.framework/Headers/tclPlatDecls.h
tkinter_embedded/Tcl.framework/Headers/tclTomMath.h
tkinter_embedded/Tcl.framework/Headers/tclTomMathDecls.h
tkinter_embedded/Tcl.framework/Headers/tommath.h
tkinter_embedded/Tcl.framework/Resources/Info.plist
tkinter_embedded/Tcl.framework/Resources/license.terms
tkinter_embedded/Tcl.framework/Resources/tclConfig.sh
tkinter_embedded/Tcl.framework/Resources/tclooConfig.sh
tkinter_embedded/Tcl.framework/Resources/Scripts/auto.tcl
tkinter_embedded/Tcl.framework/Resources/Scripts/clock.tcl
tkinter_embedded/Tcl.framework/Resources/Scripts/foreachline.tcl
tkinter_embedded/Tcl.framework/Resources/Scripts/history.tcl
tkinter_embedded/Tcl.framework/Resources/Scripts/icu.tcl
tkinter_embedded/Tcl.framework/Resources/Scripts/init.tcl
tkinter_embedded/Tcl.framework/Resources/Scripts/install.tcl
tkinter_embedded/Tcl.framework/Resources/Scripts/package.tcl
tkinter_embedded/Tcl.framework/Resources/Scripts/parray.tcl
tkinter_embedded/Tcl.framework/Resources/Scripts/readfile.tcl
tkinter_embedded/Tcl.framework/Resources/Scripts/safe.tcl
tkinter_embedded/Tcl.framework/Resources/Scripts/tclAppInit.c
tkinter_embedded/Tcl.framework/Resources/Scripts/tclDTrace.d
tkinter_embedded-9.0.1.1.dist-info/METADATA
tkinter_embedded-9.0.1.1.dist-info/WHEEL
tkinter_embedded-9.0.1.1.dist-info/top_level.txt
tkinter_embedded-9.0.1.1.dist-info/RECORD
